{"cursor":"1803","size":15,"audio":[],"currentlang":"en","article":"\n\nA 'command' in military terminology is an organisational unit for which the\nindividual in [[Military command]] is responsible. A Commander will normally be\nspecifically appointed to the role in order to provide a legal framework for the\nauthority bestowed. Naval and military officers have legal authority by virtue\nof their officer's commission, however the specific responsibilities and\nprivileges of command are derived from the publication of appointment.\n\nThe United States Department of Defense defines command as follows: United\nStates Department of Defense,\n[http://www.dtic.mil/doctrine/jel/doddict/data/c/3223.html DOD Definition of\ncommand]\n\n{{quote|(DOD) 1. The authority that a commander in the armed forces lawfully\nexercises over subordinates by virtue of rank or assignment. Command includes\nthe authority and responsibility for effectively using available resources and\nfor planning the employment of, organizing, directing, coordinating, and\ncontrolling military forces for the accomplishment of assigned missions. It also\nincludes responsibility for health, welfare, morale, and discipline of assigned\npersonnel.\n\n(DOD) 2. An order given by a commander; that is, the will of the commander\nexpressed for the purpose of bringing about a particular action.\n\n(DOD) 3. A unit or units, an organization, or an area under the command of one\nindividual. Also called CMD. See also area command; combatant command; combatant\ncommand (command authority).}}\n","linknr":183,"url":"Command_(military_formation)","recorded":1364215319,"links":["/w/index.php?title=Command_(military_formation)&action=edit","/w/index.php?title=Command_(military_formation)&action=edit","//en.wikipedia.org/apple-touch-icon.png","//bits.wikimedia.org/favicon/wikipedia.ico","/w/opensearch_desc.php","//en.wikipedia.org/w/api.php?action=rsd","//creativecommons.org/licenses/by-sa/3.0/","/w/index.php?title=Special:RecentChanges&feed=atom","//bits.wikimedia.org/en.wikipedia.org/load.php?debug=false&lang=en&modules=ext.gadget.DRN-wizard%2CReferenceTooltips%2Ccharinsert%2Cteahouse%7Cext.wikihiero%7Cmediawiki.legacy.commonPrint%2Cshared%7Cmw.PopUpMediaTransform%7Cskins.vector&only=styles&skin=vector&*","//bits.wikimedia.org/en.wikipedia.org/load.php?debug=false&lang=en&modules=site&only=styles&skin=vector&*","//bits.wikimedia.org/en.wikipedia.org/load.php?debug=false&lang=en&modules=startup&only=scripts&skin=vector&*","//bits.wikimedia.org/geoiplookup","//meta.wikimedia.org","#mw-head","#p-search","/wiki/War","/wiki/Category:Military_history_by_period","/wiki/Prehistoric_warfare","/wiki/Ancient_warfare","/wiki/Medieval_warfare","/wiki/Early_modern_warfare","/wiki/Industrial_warfare","/wiki/Modern_warfare","/wiki/First_generation_warfare","/wiki/Second_generation_warfare","/wiki/Third_generation_warfare","/wiki/Fourth_generation_warfare","/wiki/Battlespace","/wiki/Aerial_warfare","/wiki/Information_warfare","/wiki/Ground_warfare","/wiki/Naval_warfare","/wiki/Space_warfare","/wiki/Weapon","/wiki/Armoured_warfare","/wiki/Artillery","/wiki/Biological_warfare","/wiki/Cavalry","/wiki/Conventional_warfare","/wiki/Chemical_warfare","/wiki/Cyberweapon","/wiki/Electronic_warfare","/wiki/Infantry","/wiki/Nuclear_warfare","/wiki/Psychological_warfare","/wiki/Unconventional_warfare","/wiki/Military_tactics","/wiki/Air_combat_manoeuvring","/wiki/Battle","/wiki/Cavalry_tactics","/wiki/Charge_(warfare)","/wiki/Cover_(military)","/wiki/Counter-insurgency","/wiki/Defensive_fighting_position","/wiki/Guerrilla_warfare","/wiki/Morale","/wiki/Siege","/wiki/Tactical_objective","/wiki/Operational_level_of_war","/wiki/Blitzkrieg","/wiki/Soviet_deep_battle","/wiki/Maneuver_warfare","/wiki/Operational_manoeuvre_group","/wiki/Military_strategy","/wiki/Attrition_warfare","/wiki/Military_deception","/wiki/Strategic_defence","/wiki/Offensive_(military)","/wiki/Strategic_goal_(military)","/wiki/Naval_strategy","/wiki/Grand_strategy","/wiki/Containment","/wiki/Economic_warfare","/wiki/Military_science","/wiki/Philosophy_of_war","/wiki/Strategic_studies","/wiki/Total_war","/wiki/Military_organization","/wiki/Command_and_control_(military)","/wiki/Doctrine","/wiki/Military_education_and_training","/wiki/Military_engineering","/wiki/Military_intelligence","/wiki/Military_rank","/wiki/Staff_(military)","/wiki/Military_technology_and_equipment","/wiki/Military_logistics","/wiki/Materiel","/wiki/Military_supply_chain_management","/wiki/Asymmetric_warfare","/wiki/Cold_war_(general_term)","/wiki/Mercenary","/wiki/Military_operation","/wiki/Operations_research","/wiki/Principles_of_War","/wiki/Proxy_war","/wiki/Trench_warfare","/wiki/War_crimes","/wiki/Category:Military_lists","/wiki/List_of_battles","/w/index.php?title=List_of_military_commanders&action=edit&redlink=1","/wiki/List_of_military_operations","/wiki/List_of_sieges","/wiki/Lists_of_wars","/wiki/List_of_war_crimes","/wiki/Lists_of_weapons","/wiki/List_of_military_writers","/wiki/Template:War","/wiki/Template_talk:War","//en.wikipedia.org/w/index.php?title=Template:War&action=edit","/wiki/Military_terminology","/w/index.php?title=Military_command&action=edit&redlink=1","/wiki/Commissioned_officer","/wiki/United_States_Department_of_Defense","#cite_note-1","/w/index.php?title=Command_(military_formation)&action=edit&section=1","/wiki/Command_and_control","/wiki/Chain_of_command","/w/index.php?title=Command_(military_formation)&action=edit&section=2","#cite_ref-1","/wiki/United_States_Department_of_Defense","http://www.dtic.mil/doctrine/jel/doddict/data/c/3223.html","http://en.wikipedia.org/w/index.php?title=Command_(military_formation)&oldid=540562136","/wiki/Help:Categories","/wiki/Category:Military_units_and_formations_by_size","/wiki/Category:Commands_(military_formations)","/wiki/Category:Command_and_control","/w/index.php?title=Special:UserLogin&returnto=Command+%28military+formation%29&type=signup","/w/index.php?title=Special:UserLogin&returnto=Command+%28military+formation%29","/wiki/Command_(military_formation)","/wiki/Talk:Command_(military_formation)","#","/wiki/Command_(military_formation)","/w/index.php?title=Command_(military_formation)&action=edit","/w/index.php?title=Command_(military_formation)&action=history","#","/w/index.php","//bits.wikimedia.org/static-1.21wmf11/skins/vector/images/search-ltr.png?303-4","/wiki/Main_Page","/wiki/Main_Page","/wiki/Portal:Contents","/wiki/Portal:Featured_content","/wiki/Portal:Current_events","/wiki/Special:Random","//donate.wikimedia.org/wiki/Special:FundraiserRedirector?utm_source=donate&utm_medium=sidebar&utm_campaign=C13_en.wikipedia.org&uselang=en","/wiki/Help:Contents","/wiki/Wikipedia:About","/wiki/Wikipedia:Community_portal","/wiki/Special:RecentChanges","/wiki/Wikipedia:Contact_us","/wiki/Special:WhatLinksHere/Command_(military_formation)","/wiki/Special:RecentChangesLinked/Command_(military_formation)","/wiki/Wikipedia:File_Upload_Wizard","/wiki/Special:SpecialPages","/w/index.php?title=Command_(military_formation)&oldid=540562136","/w/index.php?title=Command_(military_formation)&action=info","/w/index.php?title=Special:Cite&page=Command_%28military_formation%29&id=540562136","/w/index.php?title=Special:Book&bookcmd=book_creator&referer=Command+%28military+formation%29","/w/index.php?title=Special:Book&bookcmd=render_article&arttitle=Command+%28military+formation%29&oldid=540562136&writer=rl","/w/index.php?title=Command_(military_formation)&printable=yes","//ca.wikipedia.org/wiki/Comandament_(unitat_militar)","//de.wikipedia.org/wiki/Kommando_(milit%C3%A4rische_Dienststelle)","//es.wikipedia.org/wiki/Mando_(unidad_militar)","//ja.wikipedia.org/wiki/%E3%82%B3%E3%83%9E%E3%83%B3%E3%83%89_(%E9%83%A8%E9%9A%8A%E7%B7%A8%E6%88%90)","//pl.wikipedia.org/wiki/dow%C3%B3dztwo","//simple.wikipedia.org/wiki/Command_(military)","//vi.wikipedia.org/wiki/B%E1%BB%99_t%C6%B0_l%E1%BB%87nh","//www.wikidata.org/wiki/Special:ItemByTitle/enwiki/Command (military formation)","//en.wikipedia.org/wiki/Wikipedia:Text_of_Creative_Commons_Attribution-ShareAlike_3.0_Unported_License","//creativecommons.org/licenses/by-sa/3.0/","//wikimediafoundation.org/wiki/Terms_of_Use","//www.wikimediafoundation.org/","//en.wikipedia.org/wiki/Wikipedia:Contact_us","//wikimediafoundation.org/wiki/Privacy_policy","/wiki/Wikipedia:About","/wiki/Wikipedia:General_disclaimer","http://en.m.wikipedia.org/wiki/Command_(military_formation)","//wikimediafoundation.org/","//bits.wikimedia.org/images/wikimedia-button.png","//www.mediawiki.org/","//bits.wikimedia.org/static-1.21wmf11/skins/common/images/poweredby_mediawiki_88x31.png","//bits.wikimedia.org/en.wikipedia.org/load.php?debug=false&lang=en&modules=skins.vector&only=scripts&skin=vector&*","/w/index.php?title=MediaWiki:Gadget-ReferenceTooltips.js&action=raw&ctype=text/javascript&508635914","//bits.wikimedia.org/en.wikipedia.org/load.php?debug=false&lang=en&modules=site&only=scripts&skin=vector&*"],"instances":[],"pdf":[],"categories":["Military units and formations by size","Commands (military formations)|*","Command and control"],"headings":["See also","Notes"],"image":["//bits.wikimedia.org/static-1.21wmf11/skins/vector/images/search-ltr.png?303-4","//bits.wikimedia.org/images/wikimedia-button.png","//bits.wikimedia.org/static-1.21wmf11/skins/common/images/poweredby_mediawiki_88x31.png"],"tags":[],"members":[],"related":["Military_terminology","Commissioned_officer","United_States_Department_of_Defense","United_States_Department_of_Defense","Command_and_control","Chain_of_command"]}